ci_messages/__init__.py
ci_messages/config.py
ci_messages/schema.py
ci_messages-0.2.1.dist-info/COPYING
ci_messages-0.2.1.dist-info/METADATA
ci_messages-0.2.1.dist-info/WHEEL
ci_messages-0.2.1.dist-info/entry_points.txt
ci_messages-0.2.1.dist-info/top_level.txt
ci_messages-0.2.1.dist-info/RECORD
