Metadata-Version: 2.1
Name: ci-messages
Version: 0.2.1
Summary: Python wrapper for CI Messages schemas
Home-page: https://pagure.io/fedora-ci/python-ci_messages
Author: Adam Williamson
Author-email: awilliam@redhat.com
License: GPLv3+
Classifier: Development Status :: 5 - Production/Stable
Classifier: License :: OSI Approved :: GNU General Public License v3 or later (GPLv3+)
Classifier: Operating System :: POSIX :: Linux
Classifier: Programming Language :: Python :: 3
Classifier: Programming Language :: Python :: 3.6
Classifier: Programming Language :: Python :: 3.7
Classifier: Programming Language :: Python :: 3.8
Classifier: Programming Language :: Python :: 3.9
Classifier: Programming Language :: Python :: 3.10
Classifier: Programming Language :: Python :: 3.11
Requires-Python: !=3.0.*, !=3.1.*, !=3.2.*, !=3.3.*, !=3.4.*, !=3.5.*, <4
License-File: COPYING
Requires-Dist: fedora-messaging
Requires-Dist: jsonref
